{
  "version": 1,
  "skills": {
    "cold-email": {
      "source": "coreyhaines31/marketingskills",
      "sourceType": "github",
      "skillPath": "skills/cold-email/SKILL.md",
      "computedHash": "a92d0fc0d4740d751716d0fa123851deecc12d56d6f30515ffc051f312362503"
    },
    "prospecting": {
      "source": "coreyhaines31/marketingskills",
      "sourceType": "github",
      "skillPath": "skills/prospecting/SKILL.md",
      "computedHash": "3a7c70ae784135394073b5f99fad2356d86e3702b169605d03c7bedacaded777"
    }
  }
}
